loraprov/__init__.py
loraprov/cli.py
loraprov/core.py
loraprov/hashing.py
loraprov/hf_filter.py
loraprov/keycli.py
loraprov/sbom.py
loraprov-0.1.2.dist-info/entry_points.txt
loraprov-0.1.2.dist-info/LICENSE
loraprov-0.1.2.dist-info/METADATA
loraprov-0.1.2.dist-info/WHEEL
loraprov-0.1.2.dist-info/RECORD
