Metadata-Version: 2.3
Name: loraprov
Version: 0.1.2
Summary: Tamper‑evident signatures and license lineage for LoRA / adapter files
License: Apache-2.0
Author: Keith Tyser
Author-email: keithtyser@gmail.com
Requires-Python: >=3.9,<4.0
Classifier: License :: OSI Approved :: Apache Software License
Classifier: Programming Language :: Python :: 3
Classifier: Programming Language :: Python :: 3.9
Classifier: Programming Language :: Python :: 3.10
Classifier: Programming Language :: Python :: 3.11
Classifier: Programming Language :: Python :: 3.12
Classifier: Programming Language :: Python :: 3.13
Requires-Dist: pynacl (>=1.5.0,<2.0.0)
Requires-Dist: rich (>=14.0.0,<15.0.0)
Requires-Dist: typer (>=0.15.2,<0.16.0)
